PYRM/PYRM.py
PYRM/TPY.py
PYRM/__init__.py
PYRM/logs.py
Pyrmc-2.4.2.dist-info/LICENSE
Pyrmc-2.4.2.dist-info/METADATA
Pyrmc-2.4.2.dist-info/WHEEL
Pyrmc-2.4.2.dist-info/top_level.txt
Pyrmc-2.4.2.dist-info/RECORD
