Metadata-Version: 2.1
Name: Pyrmc
Version: 2.4.2
Summary: console line tool to add function to be independent!
Home-page: https://github.com/
Author: pyslow_riding
Author-email: slowridingytb@gmail.com
License: UNKNOWN
Platform: UNKNOWN
Classifier: Programming Language :: Python :: 3
Classifier: License :: OSI Approved :: MIT License
Classifier: Operating System :: OS Independent
Requires-Python: >=3.6
